{
    "_id": {
        "$oid": "5fb4301933180000cb08941c"
    },
    "DisplayNameId": 137438989504,
    "LocalizedName": {
        "enMale": "Imperial Fleet",
        "frMale": "Flotte Imp\u00e9riale",
        "frFemale": "Flotte Imp\u00e9riale",
        "deMale": "Imperiale Flotte",
        "deFemale": "Imperiale Flotte"
    },
    "AreaId": 4611686351279967010,
    "ZoneName": "imperial_fleet_chat",
    "MapPages": [
        {
            "Id": 40169,
            "Guid": 137438993641,
            "SId": -2275001652588004560,
            "MapNameB62Id": "CBiGwWC",
            "MapName": "imp_flaghship_command_deck",
            "Name": "Command Deck",
            "LocalizedName": {
                "enMale": "Command Deck",
                "frMale": "Pont du commandement",
                "frFemale": "Pont du commandement",
                "deMale": "Kommandodeck",
                "deFemale": "Kommandodeck"
            },
            "ParentId": 2085850714855905034,
            "MinX": 78.57424,
            "MinY": 23.705708,
            "MinZ": -12.297499,
            "MaxX": 102.781044,
            "MaxY": 24.983377,
            "MaxZ": 11.909298,
            "IsHeroic": false,
            "MountAllowed": true,
            "HasImage": true,
            "Volume": 748.6751,
            "MiniMapVolume": 1308.334,
            "MiniMapMinX": 74.67764,
            "MiniMapMinZ": -16.1941,
            "MiniMapMaxX": 106.67764,
            "MiniMapMaxZ": 15.805901,
            "ImagePath": "\/resources\/world\/areas\/4611686351279967010\/imp_flaghship_command_deck_r.dds",
            "ExplorationId": 2,
            "MapFowRadius": 1,
            "MiniMapColumnCount": 2,
            "MiniMapRowCount": 2,
            "ExplorationType": "EXPLORABLE"
        },
        {
            "Id": 40170,
            "Guid": 137438993642,
            "SId": 7217616974470430242,
            "MapNameB62Id": "8huZq65",
            "MapName": "imp_flaghship_crew_deck",
            "Name": "Crew Deck",
            "LocalizedName": {
                "enMale": "Crew Deck",
                "frMale": "Pont de l'\u00e9quipage",
                "frFemale": "Pont de l'\u00e9quipage",
                "deMale": "Crew-Deck",
                "deFemale": "Crew-Deck"
            },
            "ParentId": 2085850714855905034,
            "MinX": 59.087753,
            "MinY": -22.658041,
            "MinZ": -6.8145494,
            "MaxX": 78.96425,
            "MaxY": -21.42196,
            "MaxZ": 13.06195,
            "IsHeroic": false,
            "MountAllowed": true,
            "HasImage": true,
            "Volume": 488.34454,
            "MiniMapVolume": 1265.7461,
            "MiniMapMinX": 53.026,
            "MiniMapMinZ": -12.8763,
            "MiniMapMaxX": 85.026,
            "MiniMapMaxZ": 19.1237,
            "ImagePath": "\/resources\/world\/areas\/4611686351279967010\/imp_flaghship_crew_deck_r.dds",
            "ExplorationId": 3,
            "MapFowRadius": 1,
            "MiniMapColumnCount": 2,
            "MiniMapRowCount": 2,
            "ExplorationType": "EXPLORABLE"
        },
        {
            "Id": 40172,
            "Guid": 137438993644,
            "SId": -4962215959373097726,
            "MapNameB62Id": "0jNAEk0",
            "MapName": "imp_flaghship_engineering",
            "Name": "Engineering",
            "LocalizedName": {
                "enMale": "Engineering",
                "frMale": "Salle des machines",
                "frFemale": "Salle des machines",
                "deMale": "Technikbereich",
                "deFemale": "Technikbereich"
            },
            "ParentId": 2085850714855905034,
            "MinX": 27.479004,
            "MinY": 11.603678,
            "MinZ": -5.7666426,
            "MaxX": 35.28447,
            "MaxY": 12.158922,
            "MaxZ": 2.0388231,
            "IsHeroic": false,
            "MountAllowed": true,
            "HasImage": true,
            "Volume": 33.82843,
            "MiniMapVolume": 142.14258,
            "MiniMapMinX": 23.381737,
            "MiniMapMinZ": -9.86391,
            "MiniMapMaxX": 39.381737,
            "MiniMapMaxZ": 6.1360903,
            "ImagePath": "\/resources\/world\/areas\/4611686351279967010\/imp_flaghship_engineering_r.dds",
            "ExplorationId": 7,
            "MapFowRadius": 1,
            "MiniMapColumnCount": 1,
            "MiniMapRowCount": 1,
            "ExplorationType": "EXPLORABLE"
        },
        {
            "Id": 40171,
            "Guid": 137438993643,
            "SId": 7003116645645936278,
            "MapNameB62Id": "bkPPC7C",
            "MapName": "imp_flaghship_hangar_deck2",
            "Name": "Hangar Deck",
            "LocalizedName": {
                "enMale": "Hangar Deck",
                "frMale": "Pont du hangar",
                "frFemale": "Pont du hangar",
                "deMale": "Hangardeck",
                "deFemale": "Hangardeck"
            },
            "ParentId": 2085850714855905034,
            "MinX": 221.85628,
            "MinY": -6.447491,
            "MinZ": -7.12557,
            "MaxX": 236.77095,
            "MaxY": -4.404185,
            "MaxZ": 7.789105,
            "IsHeroic": false,
            "MountAllowed": true,
            "HasImage": true,
            "Volume": 454.52838,
            "MiniMapVolume": 523.0864,
            "MiniMapMinX": 221.31361,
            "MiniMapMinZ": -7.6682324,
            "MiniMapMaxX": 237.31361,
            "MiniMapMaxZ": 8.331768,
            "ImagePath": "\/resources\/world\/areas\/4611686351279967010\/imp_flaghship_hangar_deck2_r.dds",
            "ExplorationId": 6,
            "MapFowRadius": 1,
            "MiniMapColumnCount": 1,
            "MiniMapRowCount": 1,
            "ExplorationType": "EXPLORABLE"
        },
        {
            "Id": 40168,
            "Guid": 137438993640,
            "SId": 2058824632609939834,
            "MapNameB62Id": "UY6AOH8",
            "MapName": "imp_flagship_bridge",
            "Name": "Bridge",
            "LocalizedName": {
                "enMale": "Bridge",
                "frMale": "Passerelle",
                "frFemale": "Passerelle",
                "deMale": "Br\u00fccke",
                "deFemale": "Br\u00fccke"
            },
            "ParentId": 2085850714855905034,
            "MinX": 82.74582,
            "MinY": 18.836847,
            "MinZ": -7.3588724,
            "MaxX": 102.64545,
            "MaxY": 20.39438,
            "MaxZ": 12.540748,
            "IsHeroic": false,
            "MountAllowed": true,
            "HasImage": true,
            "Volume": 616.7754,
            "MiniMapVolume": 797.45703,
            "MiniMapMinX": 76.69563,
            "MiniMapMinZ": -5.409063,
            "MiniMapMaxX": 108.69563,
            "MiniMapMaxZ": 10.590937,
            "ImagePath": "\/resources\/world\/areas\/4611686351279967010\/imp_flagship_bridge_r.dds",
            "ExplorationId": 5,
            "MapFowRadius": 1,
            "MiniMapColumnCount": 1,
            "MiniMapRowCount": 2,
            "ExplorationType": "EXPLORABLE"
        },
        {
            "Id": 40205,
            "Guid": 137438993677,
            "SId": -2884086086151433607,
            "MapNameB62Id": "UH9CDVC",
            "MapName": "imp_flagship_officer_deck",
            "Name": "Officer Deck",
            "LocalizedName": {
                "enMale": "Officer Deck",
                "frMale": "Pont des officiers",
                "frFemale": "Pont des officiers",
                "deMale": "Offiziersdeck",
                "deFemale": "Offiziersdeck"
            },
            "ParentId": 2085850714855905034,
            "MinX": 220.87263,
            "MinY": -4.534811,
            "MinZ": -5.051167,
            "MaxX": 231.75377,
            "MaxY": -3.5914369,
            "MaxZ": 5.829967,
            "IsHeroic": false,
            "MountAllowed": true,
            "HasImage": true,
            "Volume": 111.694626,
            "MiniMapVolume": 241.50378,
            "MiniMapMinX": 218.3132,
            "MiniMapMinZ": -7.6105995,
            "MiniMapMaxX": 234.3132,
            "MiniMapMaxZ": 8.3894005,
            "ImagePath": "\/resources\/world\/areas\/4611686351279967010\/imp_flagship_officer_deck_r.dds",
            "ExplorationId": 4,
            "MapFowRadius": 1,
            "MiniMapColumnCount": 1,
            "MiniMapRowCount": 1,
            "ExplorationType": "EXPLORABLE"
        },
        {
            "Id": 40148,
            "Guid": 137438993620,
            "SId": 2085850714855905034,
            "MapNameB62Id": "2XTxWIC",
            "MapName": "world_map",
            "Name": "Harrower-Class Dreadnought",
            "LocalizedName": {
                "enMale": "Harrower-Class Dreadnought",
                "frMale": "Cuirass\u00e9 de classe Pourfendeur",
                "frFemale": "Cuirass\u00e9 de classe Pourfendeur",
                "deMale": "Schlachtschiff der Harrower-Klasse",
                "deFemale": "Schlachtschiff der Harrower-Klasse"
            },
            "ParentId": 0,
            "MinX": -77.31146,
            "MinY": 136.70834,
            "MinZ": -240.09528,
            "MaxX": 407.7895,
            "MaxY": 196.71185,
            "MaxZ": 245.00568,
            "IsHeroic": false,
            "MountAllowed": true,
            "HasImage": true,
            "Volume": 14120202,
            "MiniMapVolume": 7864780,
            "MiniMapMinX": -90.761,
            "MiniMapMinZ": -125.5448,
            "MiniMapMaxX": 421.239,
            "MiniMapMaxZ": 130.4552,
            "ImagePath": "\/resources\/world\/areas\/4611686351279967010\/world_map_r.dds",
            "ExplorationId": 1,
            "MapFowRadius": 1,
            "MiniMapColumnCount": 8,
            "MiniMapRowCount": 16,
            "ExplorationType": "EXPLORABLE"
        }
    ],
    "MapNotes": {
        "4611686302248354023": {
            "PositionX": 81.3929,
            "PositionY": 24,
            "PositionZ": -0.2548,
            "Rotation": 90,
            "MapTags": {
                "imp_flaghship_command_deck": true
            },
            "ParentMapTag": "imp_flaghship_command_deck",
            "ShowGhosted": false,
            "ShowOffmapArrow": false,
            "ShowQuestBreadcrumbOnly": false,
            "DoNotBreadcrumb": false,
            "IgnoreFoW": false,
            "TemplateFQN": "mpn.housing.imp_flagship.to_wnk_command_deck",
            "MPNB62Id": "ApUvdiE",
            "Id": "0",
            "Base62Id": "0000000"
        },
        "4611686302248354024": {
            "PositionX": 60.6988,
            "PositionY": -21.95,
            "PositionZ": 3.15,
            "Rotation": 90,
            "MapTags": {
                "imp_flaghship_crew_deck": true
            },
            "ParentMapTag": "imp_flaghship_crew_deck",
            "ShowGhosted": false,
            "ShowOffmapArrow": false,
            "ShowQuestBreadcrumbOnly": false,
            "DoNotBreadcrumb": false,
            "IgnoreFoW": false,
            "TemplateFQN": "mpn.housing.imp_flagship.to_wnk_command_deck",
            "MPNB62Id": "ApUvdiE",
            "Id": "0",
            "Base62Id": "0000000"
        },
        "4611686302248354026": {
            "PositionX": 222.3183,
            "PositionY": -6.2,
            "PositionZ": 0.3468,
            "Rotation": 90,
            "MapTags": {
                "imp_flaghship_hangar_deck2": true
            },
            "ParentMapTag": "imp_flaghship_hangar_deck2",
            "ShowGhosted": false,
            "ShowOffmapArrow": false,
            "ShowQuestBreadcrumbOnly": false,
            "DoNotBreadcrumb": false,
            "IgnoreFoW": false,
            "TemplateFQN": "mpn.housing.imp_flagship.to_wnk_hangar",
            "MPNB62Id": "PF1KTa2",
            "Id": "0",
            "Base62Id": "0000000"
        },
        "4611686302248354028": {
            "PositionX": 35.0925,
            "PositionY": 11.65,
            "PositionZ": -2.8485,
            "Rotation": -90,
            "MapTags": {
                "imp_flaghship_engineering": true
            },
            "ParentMapTag": "imp_flaghship_engineering",
            "ShowGhosted": false,
            "ShowOffmapArrow": false,
            "ShowQuestBreadcrumbOnly": false,
            "DoNotBreadcrumb": false,
            "IgnoreFoW": false,
            "TemplateFQN": "mpn.housing.imp_flagship.to_wnk_engineering",
            "MPNB62Id": "LlrFgLB",
            "Id": "0",
            "Base62Id": "0000000"
        },
        "4611686302248354030": {
            "PositionX": 84.1846,
            "PositionY": 19.2974,
            "PositionZ": -3.8182,
            "Rotation": 90,
            "MapTags": {
                "imp_flaghship_bridge": true
            },
            "ParentMapTag": "imp_flaghship_bridge",
            "ShowGhosted": false,
            "ShowOffmapArrow": false,
            "ShowQuestBreadcrumbOnly": false,
            "DoNotBreadcrumb": false,
            "IgnoreFoW": false,
            "TemplateFQN": "mpn.housing.imp_flagship.to_wnk_bridge_officers",
            "MPNB62Id": "adJcda4",
            "Id": "0",
            "Base62Id": "0000000"
        },
        "4611686302248354032": {
            "PositionX": 221.455,
            "PositionY": -4.5,
            "PositionZ": 0.3402,
            "Rotation": 90,
            "MapTags": {
                "imp_flaghship_officer_deck": true
            },
            "ParentMapTag": "imp_flaghship_officer_deck",
            "ShowGhosted": false,
            "ShowOffmapArrow": false,
            "ShowQuestBreadcrumbOnly": false,
            "DoNotBreadcrumb": false,
            "IgnoreFoW": false,
            "TemplateFQN": "mpn.housing.imp_flagship.to_wnk_officers_deck",
            "MPNB62Id": "4U9FhX3",
            "Id": "0",
            "Base62Id": "0000000"
        },
        "4611686302248354035": {
            "PositionX": 84.3721,
            "PositionY": 19.3,
            "PositionZ": 0.0966,
            "Rotation": 90,
            "MapTags": {
                "imp_flaghship_bridge": true
            },
            "ParentMapTag": "imp_flaghship_bridge",
            "ShowGhosted": false,
            "ShowOffmapArrow": false,
            "ShowQuestBreadcrumbOnly": false,
            "DoNotBreadcrumb": false,
            "IgnoreFoW": false,
            "TemplateFQN": "mpn.housing.imp_flagship.to_wnk_bridge",
            "MPNB62Id": "a2ZGfo0",
            "Id": "0",
            "Base62Id": "0000000"
        }
    },
    "Id": "4611686351279967010",
    "Base62Id": "8akFVqD",
    "Name": "Imperial Fleet",
    "B62References": [],
    "first_seen": "2.9.0",
    "last_seen": "6.3.2b",
    "current_version": "6.3.2b",
    "hash": "867463703",
    "removed_in": "",
    "changed_fields": [
        "B62References",
        "ExplorationType",
        "AreaDat",
        "hash"
    ],
    "previous_versions": [
        "2.9.0",
        "2.10.0",
        "3.3.1",
        "3.3.2",
        "5.10.0",
        "6.3.0a"
    ],
    "AreaDat": {
        "AreaId": "4611686351279967010",
        "AreaGuid": "4611686301371875341",
        "AssetDefs": {
            "4611686301518104000": "\\spn\\stronghold\\flagships\\imp\\elevator.spn_p",
            "4611686302147104926": "\\spn\\location\\universal\\training_dummy_invis_target.spn_p",
            "4611686302147104928": "\\spn\\location\\flashpoint\\raid\\eternity_vault\\taxi\\escape_pod_imp_07.spn_p",
            "4611686302147104940": "\\spn\\location\\flashpoint\\raid\\eternity_vault\\taxi\\escape_pod_imp_02.spn_p",
            "4611686302147104950": "\\enc\\location\\flashpoint\\raid\\eternity_vault\\flavor\\enc_imp_ship_crew.enc",
            "4611686302147104951": "\\f:enc.location.flashpoint.raid.eternity_vault.flavor.enc_imp_ship_crew.spn_c",
            "4611686302147104952": "\\c:enc.location.flashpoint.raid.eternity_vault.flavor.enc_imp_ship_crew.spn_c",
            "4611686302147104955": "\\spn\\location\\flashpoint\\raid\\eternity_vault\\object\\cinematic_imperial.spn_p",
            "4611686302147104962": "\\spn\\location\\raid\\shared\\eternity_vault\\imperial\\medcenter_imperial.spn_p",
            "4611686302147104965": "\\spn\\location\\flashpoint\\raid\\eternity_vault\\taxi\\escape_pod_imp_08.spn_p",
            "4611686302147104966": "\\spn\\location\\flashpoint\\raid\\eternity_vault\\object\\ship_alarm.spn_p",
            "4611686302147104984": "\\b:enc.location.flashpoint.raid.eternity_vault.flavor.enc_imp_ship_crew.spn_c",
            "4611686302147104995": "\\spn\\location\\flashpoint\\raid\\eternity_vault\\taxi\\escape_pod_imp_03.spn_p",
            "4611686302147105002": "\\spn\\location\\flashpoint\\raid\\eternity_vault\\taxi\\escape_pod_imp_01.spn_p",
            "4611686302147105003": "\\g:enc.location.flashpoint.raid.eternity_vault.flavor.enc_imp_ship_crew.spn_c",
            "4611686302147105009": "\\spn\\location\\flashpoint\\raid\\eternity_vault\\taxi\\escape_pod_imp_05.spn_p",
            "4611686302147105013": "\\d:enc.location.flashpoint.raid.eternity_vault.flavor.enc_imp_ship_crew.spn_c",
            "4611686302147105015": "\\i:enc.location.flashpoint.raid.eternity_vault.flavor.enc_imp_ship_crew.spn_c",
            "4611686302147105016": "\\a:enc.location.flashpoint.raid.eternity_vault.flavor.enc_imp_ship_crew.spn_c",
            "4611686302147105021": "\\spn\\location\\flashpoint\\raid\\eternity_vault\\taxi\\escape_pod_imp_06.spn_p",
            "4611686302147105022": "\\e:enc.location.flashpoint.raid.eternity_vault.flavor.enc_imp_ship_crew.spn_c",
            "4611686302147105025": "\\spn\\location\\flashpoint\\raid\\eternity_vault\\taxi\\escape_pod_imp_04.spn_p",
            "4611686302216894637": "\\spn\\stronghold\\flagship_imp\\door\\door_command_deck_quad.spn_p",
            "4611686302216894639": "\\spn\\stronghold\\flagship_imp\\door\\door_starboard_command_room.spn_p",
            "4611686302216894641": "\\spn\\stronghold\\flagship_imp\\door\\door_port_command_room.spn_p",
            "4611686302216894643": "\\spn\\stronghold\\flagship_imp\\door\\door_forward_command_room.spn_p",
            "4611686302216894645": "\\spn\\stronghold\\flagship_imp\\door\\door_crew_deck_quad.spn_p",
            "4611686302216894647": "\\spn\\stronghold\\flagship_imp\\door\\door_crew_room_1.spn_p",
            "4611686302216894649": "\\spn\\stronghold\\flagship_imp\\door\\door_crew_room_2.spn_p",
            "4611686302216894651": "\\spn\\stronghold\\flagship_imp\\door\\door_crew_room_3.spn_p",
            "4611686302216894653": "\\spn\\stronghold\\flagship_imp\\door\\door_crew_room_5.spn_p",
            "4611686302216894655": "\\spn\\stronghold\\flagship_imp\\door\\door_crew_room_4.spn_p",
            "4611686302216894657": "\\spn\\stronghold\\flagship_imp\\door\\door_crew_room_6.spn_p",
            "4611686302216894659": "\\spn\\stronghold\\flagship_imp\\door\\door_engine_room.spn_p",
            "4611686302216894661": "\\spn\\stronghold\\flagship_imp\\door\\door_port_hangar.spn_p",
            "4611686302216894663": "\\spn\\stronghold\\flagship_imp\\door\\door_starboard_hangar.spn_p",
            "4611686302248354020": "\\server\\mpn\\housing\\imp_flagship\\to_wnk_bridge.mpn",
            "4611686302248354022": "\\server\\mpn\\housing\\imp_flagship\\to_wnk_command_deck.mpn",
            "4611686302248354025": "\\server\\mpn\\housing\\imp_flagship\\to_wnk_hangar.mpn",
            "4611686302248354027": "\\server\\mpn\\housing\\imp_flagship\\to_wnk_engineering.mpn",
            "4611686302248354029": "\\server\\mpn\\housing\\imp_flagship\\to_wnk_bridge_officers.mpn",
            "4611686302248354031": "\\server\\mpn\\housing\\imp_flagship\\to_wnk_officers_deck.mpn",
            "4611686302364574000": "\\spn\\stronghold\\flagship_imp\\console\\command_console.spn_p",
            "4611686302364574002": "\\spn\\stronghold\\flagship_imp\\cinematic\\shuttle_arrival.spn_p",
            "4611686302392744001": "\\spn\\stronghold\\flagship_imp\\door\\escape_pod.spn_p",
            "4611686302400934000": "\\spn\\stronghold\\flagship_imp\\travel\\guildship_transitions.spn_p",
            "4611686302400934002": "\\spn\\stronghold\\flagship_imp\\travel\\hyperspace.spn_p",
            "4611686351330187070": "\\spn\\test\\path\\seed_point.spn_c",
            "4611686352163607233": "\\spn\\stronghold\\flagships\\imp\\officer_elevator.spn_p",
            "4611686352384837002": "\\spn\\stronghold\\flagship_imp\\door\\door_hangar_access.spn_p"
        },
        "B62RoomIds": {
            "_everywhere_": "0I9BZtF",
            "Default": "0Y9BZtF",
            "skyscene": "0o9BZtF",
            "imp_guildship_bridge_bridge": "129BZtF",
            "imp_guildship_bridge_elevator": "1I9BZtF",
            "imp_guildship_bridge_hall_1": "1Y9BZtF",
            "imp_guildship_bridge_hall_2": "1o9BZtF",
            "imp_guildship_bridge_room_1": "229BZtF",
            "imp_guildship_bridge_escape_pod": "2I9BZtF",
            "imp_guildship_exterior": "2Y9BZtF",
            "imp_guildship_hanger_hanger_right": "2o9BZtF",
            "imp_guildship_hanger_hanger_left": "329BZtF",
            "imp_guildship_hanger_hall_left": "3I9BZtF",
            "imp_guildship_hanger_hall_right": "3Y9BZtF",
            "imp_guildship_hanger_hall_center": "3o9BZtF",
            "imp_guildship_hanger_elevator": "429BZtF",
            "imp_guildship_crew_elevator": "4I9BZtF",
            "imp_guildship_crew_hall_center": "4Y9BZtF",
            "imp_guildship_crew_crew_room_left_01": "4o9BZtF",
            "imp_guildship_crew_crew_room_left_02": "529BZtF",
            "imp_guildship_crew_crew_room_left_03": "5I9BZtF",
            "imp_guildship_crew_crew_room_right_01": "5Y9BZtF",
            "imp_guildship_crew_crew_room_right_02": "5o9BZtF",
            "imp_guildship_crew_crew_room_right_03": "629BZtF",
            "imp_guildship_crew_hall_right": "6I9BZtF",
            "imp_guildship_crew_hall_left": "6Y9BZtF",
            "imp_guildship_engineering_elevator": "6o9BZtF",
            "imp_guildship_engineering_engineering": "729BZtF",
            "imp_guildship_executive_executive_room": "7I9BZtF",
            "imp_guildship_executive_elevator": "7Y9BZtF",
            "imp_guildship_bridge_exterior": "7o9BZtF",
            "imp_guildship_command_elevator": "829BZtF",
            "imp_guildship_command_center": "8I9BZtF",
            "imp_guildship_command_room_medium_01": "8Y9BZtF",
            "imp_guildship_command_room_large_01": "8o9BZtF",
            "imp_guildship_command_room_large_02": "929BZtF",
            "cine_spacescene_room": "9I9BZtF",
            "imp_guildship_pvp_arena": "9Y9BZtF"
        },
        "B62References": [],
        "Base62Id": "8akFVqD",
        "Id": "4611686351279967010"
    },
    "ExplorationType": "EXPLORABLE"
}